{
  "params": {},
  "original_graph": {
    "directed": false,
    "multigraph": false,
    "graph": {},
    "nodes": [
      {
        "pos": [
          10.3164,
          76.8288
        ],
        "id": 164
      },
      {
        "pos": [
          10.3006,
          77.18
        ],
        "id": 196
      },
      {
        "pos": [
          33.865,
          54.2816
        ],
        "id": 155
      },
      {
        "pos": [
          34.3853,
          54.0867
        ],
        "id": 187
      },
      {
        "pos": [
          35.7272,
          86.3223
        ],
        "id": 144
      },
      {
        "pos": [
          35.8036,
          85.7424
        ],
        "id": 160
      },
      {
        "pos": [
          4.1134,
          31.9852
        ],
        "id": 19
      },
      {
        "pos": [
          4.2264,
          32.5853
        ],
        "id": 145
      },
      {
        "pos": [
          22.911,
          11.2888
        ],
        "id": 43
      },
      {
        "pos": [
          23.2931,
          11.8072
        ],
        "id": 48
      },
      {
        "pos": [
          12.8335,
          3.5774
        ],
        "id": 103
      },
      {
        "pos": [
          13.4923,
          3.6981
        ],
        "id": 175
      },
      {
        "pos": [
          15.3929,
          42.7532
        ],
        "id": 33
      },
      {
        "pos": [
          16.1343,
          42.8686
        ],
        "id": 142
      },
      {
        "pos": [
          38.74,
          7.7922
        ],
        "id": 15
      },
      {
        "pos": [
          38.2284,
          8.4093
        ],
        "id": 65
      },
      {
        "pos": [
          48.3362,
          67.0359
        ],
        "id": 110
      },
      {
        "pos": [
          47.5427,
          67.5132
        ],
        "id": 131
      },
      {
        "pos": [
          14.0143,
          4.6001
        ],
        "id": 42
      },
      {
        "pos": [
          20.2349,
          50.7557
        ],
        "id": 106
      },
      {
        "pos": [
          20.6574,
          51.732
        ],
        "id": 138
      },
      {
        "pos": [
          3.654,
          8.1347
        ],
        "id": 38
      },
      {
        "pos": [
          3.2261,
          9.1693
        ],
        "id": 47
      },
      {
        "pos": [
          49.5734,
          61.59
        ],
        "id": 0
      },
      {
        "pos": [
          49.6214,
          60.3898
        ],
        "id": 59
      },
      {
        "pos": [
          3.7557,
          52.1485
        ],
        "id": 80
      },
      {
        "pos": [
          3.6464,
          53.351
        ],
        "id": 156
      },
      {
        "pos": [
          49.4401,
          40.1843
        ],
        "id": 51
      },
      {
        "pos": [
          48.7053,
          41.1522
        ],
        "id": 135
      },
      {
        "pos": [
          22.0889,
          34.2901
        ],
        "id": 31
      },
      {
        "pos": [
          21.3625,
          33.2603
        ],
        "id": 178
      },
      {
        "pos": [
          25.4517,
          54.0729
        ],
        "id": 17
      },
      {
        "pos": [
          26.5483,
          53.4313
        ],
        "id": 76
      },
      {
        "pos": [
          19.0766,
          50.1167
        ],
        "id": 78
      },
      {
        "pos": [
          53.3675,
          6.1132
        ],
        "id": 21
      },
      {
        "pos": [
          54.2659,
          5.0983
        ],
        "id": 102
      },
      {
        "pos": [
          37.0621,
          35.0554
        ],
        "id": 143
      },
      {
        "pos": [
          35.8218,
          35.604
        ],
        "id": 162
      },
      {
        "pos": [
          31.4682,
          89.0992
        ],
        "id": 100
      },
      {
        "pos": [
          32.7178,
          88.4693
        ],
        "id": 150
      },
      {
        "pos": [
          38.8733,
          18.7149
        ],
        "id": 10
      },
      {
        "pos": [
          39.1379,
          17.3359
        ],
        "id": 169
      },
      {
        "pos": [
          9.6921,
          57.1542
        ],
        "id": 36
      },
      {
        "pos": [
          10.0933,
          58.517
        ],
        "id": 136
      },
      {
        "pos": [
          17.8782,
          8.6456
        ],
        "id": 186
      },
      {
        "pos": [
          18.5485,
          9.9107
        ],
        "id": 191
      },
      {
        "pos": [
          9.0049,
          46.4701
        ],
        "id": 94
      },
      {
        "pos": [
          8.2186,
          47.7061
        ],
        "id": 188
      },
      {
        "pos": [
          24.7523,
          11.6275
        ],
        "id": 13
      },
      {
        "pos": [
          36.7344,
          8.4817
        ],
        "id": 193
      },
      {
        "pos": [
          28.7293,
          26.6021
        ],
        "id": 87
      },
      {
        "pos": [
          28.0998,
          27.9731
        ],
        "id": 147
      },
      {
        "pos": [
          20.5977,
          34.8134
        ],
        "id": 92
      },
      {
        "pos": [
          56.7782,
          30.4344
        ],
        "id": 41
      },
      {
        "pos": [
          55.4543,
          31.361
        ],
        "id": 61
      },
      {
        "pos": [
          13.3394,
          41.4853
        ],
        "id": 16
      },
      {
        "pos": [
          12.1092,
          40.4368
        ],
        "id": 25
      },
      {
        "pos": [
          31.18,
          56.9493
        ],
        "id": 125
      },
      {
        "pos": [
          32.4792,
          55.699
        ],
        "id": 198
      },
      {
        "pos": [
          22.4227,
          44.1802
        ],
        "id": 40
      },
      {
        "pos": [
          20.606,
          44.2689
        ],
        "id": 93
      },
      {
        "pos": [
          58.2029,
          81.2433
        ],
        "id": 2
      },
      {
        "pos": [
          57.8162,
          83.0557
        ],
        "id": 124
      },
      {
        "pos": [
          29.5101,
          98.4683
        ],
        "id": 134
      },
      {
        "pos": [
          27.9806,
          97.3462
        ],
        "id": 152
      },
      {
        "pos": [
          23.8353,
          98.4268
        ],
        "id": 26
      },
      {
        "pos": [
          21.9135,
          97.9979
        ],
        "id": 154
      },
      {
        "pos": [
          46.5879,
          9.1781
        ],
        "id": 62
      },
      {
        "pos": [
          44.6869,
          8.661
        ],
        "id": 67
      },
      {
        "pos": [
          5.5166,
          30.5912
        ],
        "id": 82
      },
      {
        "pos": [
          14.8341,
          6.4164
        ],
        "id": 122
      },
      {
        "pos": [
          9.6048,
          87.3425
        ],
        "id": 46
      },
      {
        "pos": [
          9.186,
          85.3637
        ],
        "id": 113
      },
      {
        "pos": [
          4.5258,
          34.5945
        ],
        "id": 63
      },
      {
        "pos": [
          29.1207,
          66.2258
        ],
        "id": 91
      },
      {
        "pos": [
          27.2675,
          65.3611
        ],
        "id": 148
      },
      {
        "pos": [
          12.1206,
          58.2423
        ],
        "id": 22
      },
      {
        "pos": [
          11.4212,
          95.5246
        ],
        "id": 50
      },
      {
        "pos": [
          9.7076,
          94.3769
        ],
        "id": 99
      },
      {
        "pos": [
          49.32,
          12.9158
        ],
        "id": 45
      },
      {
        "pos": [
          49.6451,
          15.0272
        ],
        "id": 146
      },
      {
        "pos": [
          19.9612,
          31.6413
        ],
        "id": 129
      },
      {
        "pos": [
          3.7835,
          94.3049
        ],
        "id": 98
      },
      {
        "pos": [
          5.0756,
          92.5638
        ],
        "id": 163
      },
      {
        "pos": [
          28.6898,
          52.894
        ],
        "id": 32
      },
      {
        "pos": [
          41.3392,
          59.5507
        ],
        "id": 53
      },
      {
        "pos": [
          42.8803,
          61.1503
        ],
        "id": 89
      },
      {
        "pos": [
          56.9826,
          68.5543
        ],
        "id": 126
      },
      {
        "pos": [
          59.027,
          69.5129
        ],
        "id": 192
      },
      {
        "pos": [
          10.5405,
          92.2731
        ],
        "id": 107
      },
      {
        "pos": [
          14.034,
          38.1439
        ],
        "id": 14
      },
      {
        "pos": [
          11.7846,
          37.6395
        ],
        "id": 72
      },
      {
        "pos": [
          17.4127,
          48.5159
        ],
        "id": 60
      },
      {
        "pos": [
          52.7383,
          65.4455
        ],
        "id": 7
      },
      {
        "pos": [
          55.0484,
          65.7327
        ],
        "id": 179
      },
      {
        "pos": [
          21.0276,
          54.048
        ],
        "id": 39
      },
      {
        "pos": [
          55.553,
          70.447
        ],
        "id": 111
      },
      {
        "pos": [
          23.8824,
          32.699
        ],
        "id": 127
      },
      {
        "pos": [
          16.614,
          11.3703
        ],
        "id": 123
      },
      {
        "pos": [
          55.8362,
          80.5907
        ],
        "id": 199
      },
      {
        "pos": [
          54.5037,
          24.7121
        ],
        "id": 117
      },
      {
        "pos": [
          54.1105,
          22.2878
        ],
        "id": 151
      },
      {
        "pos": [
          44.5578,
          52.3439
        ],
        "id": 44
      },
      {
        "pos": [
          47.0166,
          52.0329
        ],
        "id": 81
      },
      {
        "pos": [
          44.0179,
          0.8363
        ],
        "id": 27
      },
      {
        "pos": [
          45.6842,
          2.6853
        ],
        "id": 168
      },
      {
        "pos": [
          38.0658,
          10.9034
        ],
        "id": 30
      },
      {
        "pos": [
          51.9767,
          4.0275
        ],
        "id": 197
      },
      {
        "pos": [
          34.4916,
          38.8437
        ],
        "id": 114
      },
      {
        "pos": [
          35.8965,
          40.9302
        ],
        "id": 167
      },
      {
        "pos": [
          42.7293,
          96.9682
        ],
        "id": 8
      },
      {
        "pos": [
          40.1502,
          96.6603
        ],
        "id": 23
      },
      {
        "pos": [
          42.7273,
          50.4991
        ],
        "id": 75
      },
      {
        "pos": [
          24.6973,
          88.9217
        ],
        "id": 121
      },
      {
        "pos": [
          27.1424,
          89.9382
        ],
        "id": 137
      },
      {
        "pos": [
          49.0273,
          43.7946
        ],
        "id": 158
      },
      {
        "pos": [
          17.819,
          20.3309
        ],
        "id": 20
      },
      {
        "pos": [
          20.5569,
          19.827
        ],
        "id": 177
      },
      {
        "pos": [
          7.1158,
          63.8348
        ],
        "id": 57
      },
      {
        "pos": [
          7.7544,
          66.615
        ],
        "id": 132
      },
      {
        "pos": [
          59.1902,
          28.896
        ],
        "id": 190
      },
      {
        "pos": [
          43.3445,
          75.3875
        ],
        "id": 11
      },
      {
        "pos": [
          40.6165,
          74.4696
        ],
        "id": 105
      },
      {
        "pos": [
          11.616,
          89.6011
        ],
        "id": 6
      },
      {
        "pos": [
          38.2065,
          37.7158
        ],
        "id": 12
      },
      {
        "pos": [
          24.9524,
          21.8533
        ],
        "id": 56
      },
      {
        "pos": [
          26.7408,
          19.4848
        ],
        "id": 185
      },
      {
        "pos": [
          10.9557,
          5.8822
        ],
        "id": 3
      },
      {
        "pos": [
          54.3666,
          27.734
        ],
        "id": 4
      },
      {
        "pos": [
          39.6587,
          14.3353
        ],
        "id": 149
      },
      {
        "pos": [
          14.6788,
          72.1058
        ],
        "id": 73
      },
      {
        "pos": [
          17.6061,
          73.2124
        ],
        "id": 130
      },
      {
        "pos": [
          11.8999,
          74.0975
        ],
        "id": 159
      },
      {
        "pos": [
          52.1895,
          44.33
        ],
        "id": 173
      },
      {
        "pos": [
          3.0023,
          12.4066
        ],
        "id": 104
      },
      {
        "pos": [
          27.1297,
          32.6523
        ],
        "id": 189
      },
      {
        "pos": [
          50.1977,
          6.9677
        ],
        "id": 171
      },
      {
        "pos": [
          40.5504,
          71.1174
        ],
        "id": 90
      },
      {
        "pos": [
          23.2812,
          49.2856
        ],
        "id": 141
      },
      {
        "pos": [
          13.8146,
          14.2016
        ],
        "id": 84
      },
      {
        "pos": [
          16.7128,
          15.9822
        ],
        "id": 174
      },
      {
        "pos": [
          36.8124,
          66.8396
        ],
        "id": 52
      },
      {
        "pos": [
          38.5866,
          63.9047
        ],
        "id": 77
      },
      {
        "pos": [
          26.6734,
          48.5928
        ],
        "id": 182
      },
      {
        "pos": [
          51.7595,
          57.5812
        ],
        "id": 165
      },
      {
        "pos": [
          47.058,
          96.9655
        ],
        "id": 24
      },
      {
        "pos": [
          50.0268,
          98.9681
        ],
        "id": 118
      },
      {
        "pos": [
          1.283,
          15.5969
        ],
        "id": 34
      },
      {
        "pos": [
          8.7868,
          32.5112
        ],
        "id": 128
      },
      {
        "pos": [
          0.6267,
          55.6648
        ],
        "id": 194
      },
      {
        "pos": [
          57.9856,
          22.9562
        ],
        "id": 18
      },
      {
        "pos": [
          5.4286,
          86.5737
        ],
        "id": 157
      },
      {
        "pos": [
          11.1746,
          9.8508
        ],
        "id": 88
      },
      {
        "pos": [
          32.9053,
          96.2131
        ],
        "id": 101
      },
      {
        "pos": [
          36.9929,
          57.3173
        ],
        "id": 35
      },
      {
        "pos": [
          42.8876,
          92.8017
        ],
        "id": 166
      },
      {
        "pos": [
          12.3906,
          53.9309
        ],
        "id": 86
      },
      {
        "pos": [
          14.2672,
          98.6278
        ],
        "id": 176
      },
      {
        "pos": [
          33.3164,
          32.1973
        ],
        "id": 183
      },
      {
        "pos": [
          28.5586,
          61.2946
        ],
        "id": 181
      },
      {
        "pos": [
          43.7315,
          46.3491
        ],
        "id": 37
      },
      {
        "pos": [
          1.8439,
          28.3107
        ],
        "id": 96
      },
      {
        "pos": [
          31.133,
          48.473
        ],
        "id": 153
      },
      {
        "pos": [
          47.1153,
          56.6741
        ],
        "id": 85
      },
      {
        "pos": [
          48.0435,
          23.7602
        ],
        "id": 5
      },
      {
        "pos": [
          47.1776,
          28.2062
        ],
        "id": 108
      },
      {
        "pos": [
          59.365,
          64.1708
        ],
        "id": 161
      },
      {
        "pos": [
          36.7077,
          90.8908
        ],
        "id": 70
      },
      {
        "pos": [
          7.6887,
          2.4144
        ],
        "id": 58
      },
      {
        "pos": [
          55.5998,
          10.3524
        ],
        "id": 116
      },
      {
        "pos": [
          26.0333,
          71.7282
        ],
        "id": 66
      },
      {
        "pos": [
          29.177,
          75.3509
        ],
        "id": 184
      },
      {
        "pos": [
          45.625,
          17.7772
        ],
        "id": 9
      },
      {
        "pos": [
          54.5949,
          97.2187
        ],
        "id": 1
      },
      {
        "pos": [
          48.0272,
          35.4395
        ],
        "id": 83
      },
      {
        "pos": [
          31.9238,
          9.7609
        ],
        "id": 109
      },
      {
        "pos": [
          17.0998,
          62.2446
        ],
        "id": 28
      },
      {
        "pos": [
          12.334,
          63.7351
        ],
        "id": 71
      },
      {
        "pos": [
          34.9796,
          3.7343
        ],
        "id": 119
      },
      {
        "pos": [
          47.7044,
          72.6678
        ],
        "id": 112
      },
      {
        "pos": [
          42.3918,
          83.8952
        ],
        "id": 74
      },
      {
        "pos": [
          45.2994,
          88.1503
        ],
        "id": 95
      },
      {
        "pos": [
          0.654,
          3.5951
        ],
        "id": 97
      },
      {
        "pos": [
          0.3257,
          72.6675
        ],
        "id": 29
      },
      {
        "pos": [
          2.0866,
          67.4988
        ],
        "id": 120
      },
      {
        "pos": [
          59.7018,
          74.9425
        ],
        "id": 49
      },
      {
        "pos": [
          50.3049,
          79.9754
        ],
        "id": 64
      },
      {
        "pos": [
          50.777,
          86.8781
        ],
        "id": 172
      },
      {
        "pos": [
          19.4844,
          92.8685
        ],
        "id": 115
      },
      {
        "pos": [
          59.4411,
          35.5263
        ],
        "id": 139
      },
      {
        "pos": [
          31.7703,
          15.5131
        ],
        "id": 54
      },
      {
        "pos": [
          59.2843,
          55.26
        ],
        "id": 55
      },
      {
        "pos": [
          59.9247,
          49.5268
        ],
        "id": 133
      },
      {
        "pos": [
          27.267,
          81.155
        ],
        "id": 140
      },
      {
        "pos": [
          11.7259,
          26.6746
        ],
        "id": 69
      },
      {
        "pos": [
          41.0754,
          24.9269
        ],
        "id": 180
      },
      {
        "pos": [
          18.1917,
          86.2699
        ],
        "id": 170
      },
      {
        "pos": [
          24.769,
          4.4194
        ],
        "id": 195
      },
      {
        "pos": [
          0.4671,
          80.2433
        ],
        "id": 68
      },
      {
        "pos": [
          1.1927,
          42.1993
        ],
        "id": 79
      }
    ],
    "links": [
      {
        "length": 0.35,
        "traffic": 4.38,
        "source": 164,
        "target": 196
      },
      {
        "length": 3.16,
        "traffic": 4.36,
        "source": 164,
        "target": 159
      },
      {
        "length": 8.26,
        "traffic": 4.43,
        "source": 196,
        "target": 113
      },
      {
        "length": 0.56,
        "traffic": 80.85,
        "source": 155,
        "target": 187
      },
      {
        "length": 1.98,
        "traffic": 80.81,
        "source": 155,
        "target": 198
      },
      {
        "length": 4.15,
        "traffic": 80.88,
        "source": 187,
        "target": 35
      },
      {
        "length": 0.58,
        "traffic": 0.29,
        "source": 144,
        "target": 160
      },
      {
        "length": 3.7,
        "traffic": 0.31,
        "source": 144,
        "target": 150
      },
      {
        "length": 0.61,
        "traffic": 11.11,
        "source": 19,
        "target": 145
      },
      {
        "length": 1.98,
        "traffic": 13.5,
        "source": 19,
        "target": 82
      },
      {
        "length": 4.32,
        "traffic": 4.37,
        "source": 19,
        "target": 96
      },
      {
        "length": 2.03,
        "traffic": 11.03,
        "source": 145,
        "target": 63
      },
      {
        "length": 0.64,
        "traffic": 12.23,
        "source": 43,
        "target": 48
      },
      {
        "length": 4.57,
        "traffic": 21.33,
        "source": 43,
        "target": 191
      },
      {
        "length": 7.12,
        "traffic": 9.06,
        "source": 43,
        "target": 195
      },
      {
        "length": 1.47,
        "traffic": 12.21,
        "source": 48,
        "target": 13
      },
      {
        "length": 0.67,
        "traffic": 29.2,
        "source": 103,
        "target": 175
      },
      {
        "length": 2.97,
        "traffic": 29.18,
        "source": 103,
        "target": 3
      },
      {
        "length": 1.04,
        "traffic": 29.25,
        "source": 175,
        "target": 42
      },
      {
        "length": 0.75,
        "traffic": 60.93,
        "source": 33,
        "target": 142
      },
      {
        "length": 2.41,
        "traffic": 58.89,
        "source": 33,
        "target": 16
      },
      {
        "length": 4.69,
        "traffic": 64.97,
        "source": 142,
        "target": 93
      },
      {
        "length": 0.8,
        "traffic": 86.12,
        "source": 15,
        "target": 65
      },
      {
        "length": 6.01,
        "traffic": 86.18,
        "source": 15,
        "target": 67
      },
      {
        "length": 1.5,
        "traffic": 76.05,
        "source": 65,
        "target": 193
      },
      {
        "length": 2.5,
        "traffic": 13.47,
        "source": 65,
        "target": 30
      },
      {
        "length": 0.93,
        "traffic": 81.03,
        "source": 110,
        "target": 131
      },
      {
        "length": 4.68,
        "traffic": 81.07,
        "source": 110,
        "target": 7
      },
      {
        "length": 5.16,
        "traffic": 81.03,
        "source": 131,
        "target": 112
      },
      {
        "length": 1.99,
        "traffic": 29.27,
        "source": 42,
        "target": 122
      },
      {
        "length": 1.06,
        "traffic": 75.95,
        "source": 106,
        "target": 138
      },
      {
        "length": 1.32,
        "traffic": 13.87,
        "source": 106,
        "target": 78
      },
      {
        "length": 3.38,
        "traffic": 68.39,
        "source": 106,
        "target": 141
      },
      {
        "length": 2.35,
        "traffic": 75.95,
        "source": 138,
        "target": 39
      },
      {
        "length": 1.12,
        "traffic": 9.69,
        "source": 38,
        "target": 47
      },
      {
        "length": 5.44,
        "traffic": 6.49,
        "source": 38,
        "target": 97
      },
      {
        "length": 7.0,
        "traffic": 13.44,
        "source": 38,
        "target": 58
      },
      {
        "length": 3.25,
        "traffic": 9.63,
        "source": 47,
        "target": 104
      },
      {
        "length": 1.2,
        "traffic": 95.94,
        "source": 0,
        "target": 59
      },
      {
        "length": 4.99,
        "traffic": 95.94,
        "source": 0,
        "target": 7
      },
      {
        "length": 3.53,
        "traffic": 11.55,
        "source": 59,
        "target": 165
      },
      {
        "length": 4.48,
        "traffic": 100.0,
        "source": 59,
        "target": 85
      },
      {
        "length": 1.21,
        "traffic": 32.94,
        "source": 80,
        "target": 156
      },
      {
        "length": 6.3,
        "traffic": 32.98,
        "source": 80,
        "target": 188
      },
      {
        "length": 3.8,
        "traffic": 14.75,
        "source": 156,
        "target": 194
      },
      {
        "length": 7.14,
        "traffic": 21.59,
        "source": 156,
        "target": 36
      },
      {
        "length": 1.22,
        "traffic": 98.23,
        "source": 51,
        "target": 135
      },
      {
        "length": 4.95,
        "traffic": 98.23,
        "source": 51,
        "target": 83
      },
      {
        "length": 2.66,
        "traffic": 98.23,
        "source": 135,
        "target": 158
      },
      {
        "length": 1.26,
        "traffic": 8.47,
        "source": 31,
        "target": 178
      },
      {
        "length": 1.58,
        "traffic": 8.39,
        "source": 31,
        "target": 92
      },
      {
        "length": 2.4,
        "traffic": 13.31,
        "source": 31,
        "target": 127
      },
      {
        "length": 2.14,
        "traffic": 8.39,
        "source": 178,
        "target": 129
      },
      {
        "length": 1.27,
        "traffic": 76.04,
        "source": 17,
        "target": 76
      },
      {
        "length": 4.42,
        "traffic": 76.02,
        "source": 17,
        "target": 39
      },
      {
        "length": 2.21,
        "traffic": 76.06,
        "source": 76,
        "target": 32
      },
      {
        "length": 2.31,
        "traffic": 13.82,
        "source": 78,
        "target": 60
      },
      {
        "length": 1.36,
        "traffic": 10.0,
        "source": 21,
        "target": 102
      },
      {
        "length": 2.51,
        "traffic": 10.49,
        "source": 21,
        "target": 197
      },
      {
        "length": 3.28,
        "traffic": 27.87,
        "source": 21,
        "target": 171
      },
      {
        "length": 4.79,
        "traffic": 12.24,
        "source": 21,
        "target": 116
      },
      {
        "length": 1.36,
        "traffic": 2.08,
        "source": 143,
        "target": 162
      },
      {
        "length": 2.9,
        "traffic": 2.02,
        "source": 143,
        "target": 12
      },
      {
        "length": 3.5,
        "traffic": 13.84,
        "source": 162,
        "target": 114
      },
      {
        "length": 4.23,
        "traffic": 15.94,
        "source": 162,
        "target": 183
      },
      {
        "length": 1.4,
        "traffic": 38.04,
        "source": 100,
        "target": 150
      },
      {
        "length": 4.41,
        "traffic": 37.96,
        "source": 100,
        "target": 137
      },
      {
        "length": 4.67,
        "traffic": 38.35,
        "source": 150,
        "target": 70
      },
      {
        "length": 1.4,
        "traffic": 13.33,
        "source": 10,
        "target": 169
      },
      {
        "length": 6.59,
        "traffic": 13.3,
        "source": 10,
        "target": 180
      },
      {
        "length": 3.05,
        "traffic": 13.35,
        "source": 169,
        "target": 149
      },
      {
        "length": 1.42,
        "traffic": 13.35,
        "source": 36,
        "target": 136
      },
      {
        "length": 4.2,
        "traffic": 8.21,
        "source": 36,
        "target": 86
      },
      {
        "length": 2.05,
        "traffic": 13.31,
        "source": 136,
        "target": 22
      },
      {
        "length": 1.43,
        "traffic": 29.41,
        "source": 186,
        "target": 191
      },
      {
        "length": 3.77,
        "traffic": 29.33,
        "source": 186,
        "target": 122
      },
      {
        "length": 2.42,
        "traffic": 45.75,
        "source": 191,
        "target": 123
      },
      {
        "length": 1.46,
        "traffic": 33.02,
        "source": 94,
        "target": 188
      },
      {
        "length": 6.61,
        "traffic": 33.03,
        "source": 94,
        "target": 16
      },
      {
        "length": 4.98,
        "traffic": 68.72,
        "source": 193,
        "target": 109
      },
      {
        "length": 5.06,
        "traffic": 10.94,
        "source": 193,
        "target": 119
      },
      {
        "length": 1.51,
        "traffic": 28.94,
        "source": 87,
        "target": 147
      },
      {
        "length": 6.07,
        "traffic": 28.99,
        "source": 87,
        "target": 56
      },
      {
        "length": 4.78,
        "traffic": 28.89,
        "source": 147,
        "target": 189
      },
      {
        "length": 1.62,
        "traffic": 7.07,
        "source": 41,
        "target": 61
      },
      {
        "length": 2.86,
        "traffic": 9.55,
        "source": 41,
        "target": 190
      },
      {
        "length": 3.62,
        "traffic": 29.29,
        "source": 41,
        "target": 4
      },
      {
        "length": 5.75,
        "traffic": 12.61,
        "source": 41,
        "target": 139
      },
      {
        "length": 1.62,
        "traffic": 28.38,
        "source": 16,
        "target": 25
      },
      {
        "length": 2.82,
        "traffic": 28.37,
        "source": 25,
        "target": 72
      },
      {
        "length": 1.8,
        "traffic": 4.81,
        "source": 125,
        "target": 198
      },
      {
        "length": 5.07,
        "traffic": 4.76,
        "source": 125,
        "target": 181
      },
      {
        "length": 4.71,
        "traffic": 76.07,
        "source": 198,
        "target": 32
      },
      {
        "length": 1.82,
        "traffic": 67.01,
        "source": 40,
        "target": 93
      },
      {
        "length": 5.18,
        "traffic": 68.01,
        "source": 40,
        "target": 141
      },
      {
        "length": 1.85,
        "traffic": 8.76,
        "source": 2,
        "target": 124
      },
      {
        "length": 2.46,
        "traffic": 52.02,
        "source": 2,
        "target": 199
      },
      {
        "length": 6.48,
        "traffic": 58.94,
        "source": 2,
        "target": 49
      },
      {
        "length": 1.9,
        "traffic": 10.56,
        "source": 134,
        "target": 152
      },
      {
        "length": 4.08,
        "traffic": 10.53,
        "source": 134,
        "target": 101
      },
      {
        "length": 4.28,
        "traffic": 10.58,
        "source": 152,
        "target": 26
      },
      {
        "length": 1.97,
        "traffic": 10.62,
        "source": 26,
        "target": 154
      },
      {
        "length": 5.68,
        "traffic": 10.68,
        "source": 154,
        "target": 115
      },
      {
        "length": 1.97,
        "traffic": 86.87,
        "source": 62,
        "target": 67
      },
      {
        "length": 4.23,
        "traffic": 27.89,
        "source": 62,
        "target": 171
      },
      {
        "length": 4.63,
        "traffic": 80.12,
        "source": 62,
        "target": 45
      },
      {
        "length": 6.06,
        "traffic": 10.07,
        "source": 67,
        "target": 168
      },
      {
        "length": 3.79,
        "traffic": 13.57,
        "source": 82,
        "target": 128
      },
      {
        "length": 2.02,
        "traffic": 16.03,
        "source": 46,
        "target": 113
      },
      {
        "length": 3.02,
        "traffic": 16.04,
        "source": 46,
        "target": 6
      },
      {
        "length": 3.95,
        "traffic": 11.6,
        "source": 113,
        "target": 157
      },
      {
        "length": 8.3,
        "traffic": 10.97,
        "source": 63,
        "target": 79
      },
      {
        "length": 2.05,
        "traffic": 4.7,
        "source": 91,
        "target": 148
      },
      {
        "length": 6.31,
        "traffic": 4.61,
        "source": 91,
        "target": 66
      },
      {
        "length": 4.27,
        "traffic": 4.72,
        "source": 148,
        "target": 181
      },
      {
        "length": 5.5,
        "traffic": 13.26,
        "source": 22,
        "target": 71
      },
      {
        "length": 2.06,
        "traffic": 15.1,
        "source": 50,
        "target": 99
      },
      {
        "length": 4.21,
        "traffic": 15.07,
        "source": 50,
        "target": 176
      },
      {
        "length": 2.26,
        "traffic": 19.67,
        "source": 99,
        "target": 107
      },
      {
        "length": 4.97,
        "traffic": 4.54,
        "source": 99,
        "target": 163
      },
      {
        "length": 2.14,
        "traffic": 80.14,
        "source": 45,
        "target": 146
      },
      {
        "length": 4.87,
        "traffic": 80.95,
        "source": 146,
        "target": 9
      },
      {
        "length": 2.17,
        "traffic": 4.43,
        "source": 98,
        "target": 163
      },
      {
        "length": 2.22,
        "traffic": 80.93,
        "source": 53,
        "target": 89
      },
      {
        "length": 4.89,
        "traffic": 80.9,
        "source": 53,
        "target": 35
      },
      {
        "length": 5.1,
        "traffic": 80.93,
        "source": 89,
        "target": 77
      },
      {
        "length": 2.26,
        "traffic": 58.99,
        "source": 126,
        "target": 192
      },
      {
        "length": 2.37,
        "traffic": 11.47,
        "source": 126,
        "target": 111
      },
      {
        "length": 3.42,
        "traffic": 68.61,
        "source": 126,
        "target": 179
      },
      {
        "length": 5.47,
        "traffic": 58.98,
        "source": 192,
        "target": 49
      },
      {
        "length": 2.88,
        "traffic": 19.7,
        "source": 107,
        "target": 6
      },
      {
        "length": 2.31,
        "traffic": 8.87,
        "source": 14,
        "target": 72
      },
      {
        "length": 5.94,
        "traffic": 19.58,
        "source": 72,
        "target": 128
      },
      {
        "length": 2.33,
        "traffic": 70.46,
        "source": 7,
        "target": 179
      },
      {
        "length": 4.59,
        "traffic": 8.27,
        "source": 179,
        "target": 161
      },
      {
        "length": 3.25,
        "traffic": 13.37,
        "source": 127,
        "target": 189
      },
      {
        "length": 3.98,
        "traffic": 45.77,
        "source": 123,
        "target": 84
      },
      {
        "length": 5.57,
        "traffic": 52.01,
        "source": 199,
        "target": 64
      },
      {
        "length": 2.46,
        "traffic": 33.17,
        "source": 117,
        "target": 151
      },
      {
        "length": 3.03,
        "traffic": 29.37,
        "source": 117,
        "target": 4
      },
      {
        "length": 3.9,
        "traffic": 6.58,
        "source": 117,
        "target": 18
      },
      {
        "length": 6.24,
        "traffic": 34.75,
        "source": 151,
        "target": 5
      },
      {
        "length": 2.48,
        "traffic": 99.99,
        "source": 44,
        "target": 81
      },
      {
        "length": 2.6,
        "traffic": 99.98,
        "source": 44,
        "target": 75
      },
      {
        "length": 4.64,
        "traffic": 99.99,
        "source": 81,
        "target": 85
      },
      {
        "length": 2.49,
        "traffic": 9.94,
        "source": 27,
        "target": 168
      },
      {
        "length": 3.78,
        "traffic": 13.42,
        "source": 30,
        "target": 149
      },
      {
        "length": 2.52,
        "traffic": 13.79,
        "source": 114,
        "target": 167
      },
      {
        "length": 2.6,
        "traffic": 7.23,
        "source": 8,
        "target": 23
      },
      {
        "length": 4.17,
        "traffic": 16.56,
        "source": 8,
        "target": 166
      },
      {
        "length": 4.33,
        "traffic": 9.27,
        "source": 8,
        "target": 24
      },
      {
        "length": 4.27,
        "traffic": 99.99,
        "source": 75,
        "target": 37
      },
      {
        "length": 2.65,
        "traffic": 37.87,
        "source": 121,
        "target": 137
      },
      {
        "length": 6.54,
        "traffic": 37.86,
        "source": 121,
        "target": 115
      },
      {
        "length": 3.21,
        "traffic": 4.2,
        "source": 158,
        "target": 173
      },
      {
        "length": 5.88,
        "traffic": 99.98,
        "source": 158,
        "target": 37
      },
      {
        "length": 2.78,
        "traffic": 45.88,
        "source": 20,
        "target": 177
      },
      {
        "length": 4.49,
        "traffic": 45.84,
        "source": 20,
        "target": 174
      },
      {
        "length": 4.84,
        "traffic": 45.99,
        "source": 177,
        "target": 56
      },
      {
        "length": 2.85,
        "traffic": 4.66,
        "source": 57,
        "target": 132
      },
      {
        "length": 5.22,
        "traffic": 4.69,
        "source": 57,
        "target": 71
      },
      {
        "length": 5.74,
        "traffic": 4.59,
        "source": 132,
        "target": 120
      },
      {
        "length": 2.88,
        "traffic": 81.02,
        "source": 11,
        "target": 105
      },
      {
        "length": 5.14,
        "traffic": 81.01,
        "source": 11,
        "target": 112
      },
      {
        "length": 3.35,
        "traffic": 81.0,
        "source": 105,
        "target": 90
      },
      {
        "length": 7.37,
        "traffic": 28.94,
        "source": 6,
        "target": 170
      },
      {
        "length": 2.97,
        "traffic": 68.68,
        "source": 56,
        "target": 185
      },
      {
        "length": 6.41,
        "traffic": 68.69,
        "source": 185,
        "target": 54
      },
      {
        "length": 3.97,
        "traffic": 19.28,
        "source": 3,
        "target": 88
      },
      {
        "length": 4.76,
        "traffic": 13.46,
        "source": 3,
        "target": 58
      },
      {
        "length": 3.13,
        "traffic": 4.25,
        "source": 73,
        "target": 130
      },
      {
        "length": 3.42,
        "traffic": 4.3,
        "source": 73,
        "target": 159
      },
      {
        "length": 3.62,
        "traffic": 9.61,
        "source": 104,
        "target": 34
      },
      {
        "length": 6.2,
        "traffic": 16.02,
        "source": 189,
        "target": 183
      },
      {
        "length": 5.68,
        "traffic": 80.98,
        "source": 90,
        "target": 52
      },
      {
        "length": 3.46,
        "traffic": 3.76,
        "source": 141,
        "target": 182
      },
      {
        "length": 3.4,
        "traffic": 45.81,
        "source": 84,
        "target": 174
      },
      {
        "length": 3.43,
        "traffic": 80.96,
        "source": 52,
        "target": 77
      },
      {
        "length": 4.46,
        "traffic": 3.72,
        "source": 182,
        "target": 153
      },
      {
        "length": 7.87,
        "traffic": 11.51,
        "source": 165,
        "target": 55
      },
      {
        "length": 3.58,
        "traffic": 9.24,
        "source": 24,
        "target": 118
      },
      {
        "length": 4.89,
        "traffic": 9.17,
        "source": 118,
        "target": 1
      },
      {
        "length": 6.53,
        "traffic": 6.01,
        "source": 128,
        "target": 69
      },
      {
        "length": 5.24,
        "traffic": 48.53,
        "source": 166,
        "target": 95
      },
      {
        "length": 6.47,
        "traffic": 38.4,
        "source": 166,
        "target": 70
      },
      {
        "length": 4.53,
        "traffic": 95.95,
        "source": 5,
        "target": 108
      },
      {
        "length": 6.45,
        "traffic": 82.52,
        "source": 5,
        "target": 9
      },
      {
        "length": 7.28,
        "traffic": 97.48,
        "source": 108,
        "target": 83
      },
      {
        "length": 4.8,
        "traffic": 4.56,
        "source": 66,
        "target": 184
      },
      {
        "length": 6.11,
        "traffic": 4.54,
        "source": 184,
        "target": 140
      },
      {
        "length": 5.75,
        "traffic": 68.7,
        "source": 109,
        "target": 54
      },
      {
        "length": 4.99,
        "traffic": 8.56,
        "source": 28,
        "target": 71
      },
      {
        "length": 5.15,
        "traffic": 4.36,
        "source": 74,
        "target": 95
      },
      {
        "length": 5.62,
        "traffic": 51.98,
        "source": 95,
        "target": 172
      },
      {
        "length": 5.46,
        "traffic": 4.54,
        "source": 29,
        "target": 120
      },
      {
        "length": 7.58,
        "traffic": 4.5,
        "source": 29,
        "target": 68
      },
      {
        "length": 6.92,
        "traffic": 51.99,
        "source": 64,
        "target": 172
      },
      {
        "length": 6.72,
        "traffic": 28.98,
        "source": 115,
        "target": 170
      },
      {
        "length": 5.77,
        "traffic": 11.41,
        "source": 55,
        "target": 133
      }
    ]
  }
}